{"result":{"account_id":"OtM1cjMPHbbMHZA70VV1HaQ","account_parameters":[{"pl":"Посмотреть это объявление на сайте продавца","vl":"","p":"import_link","v":"http://ecrz.by/realty/flats/3766940/","pu":"il"},{"pl":"Юридический адрес/Адрес регистрации","vl":"","p":"company_address","v":"г. Брест ул. Гоголя 2, каб.1","pu":"ca"},{"pl":"Имя","vl":"","p":"name","v":"Единый Центр Реализации Жилья","pu":"nme"},{"pl":"УНП","vl":"","p":"vat_number","v":"290482452","pu":"vn"},{"pl":"Контактное лицо","vl":"","p":"contact_person","v":"Мария","pu":"cp"},{"pl":"Адрес","vl":"","p":"address","v":"Карбышева ул, Брест, Брестская область","pu":"ad","g":[{"gi":4,"gl":"Местоположение","go":4,"po":1}]}],"ad_id":1020628968,"ad_link":"https://re.kufar.by/vi/1020628968","ad_parameters":[{"pl":"Тип оплаты","vl":"Цена","p":"remuneration_type","v":"1","pu":"rtr"},{"pl":"Тип сделки","vl":"Продажа","p":"type","v":"sell","pu":"typ"},{"pl":"Координаты","vl":["",""],"p":"coordinates","v":[23.696874,52.094185],"pu":"gbx"},{"pl":"Категория","vl":"Квартиры","p":"category","v":1010,"pu":"cat"},{"pl":"Область","vl":"Брестская","p":"region","v":1,"pu":"rgn"},{"pl":"Город / Район","vl":"Брест","p":"area","v":"1","pu":"ar"},{"pl":"Количество комнат","vl":"1","p":"rooms","v":"1","pu":"rms","g":[{"gi":2,"gl":"О квартире","go":2,"po":1},{"gi":1,"go":1,"po":1}]},{"pl":"Цена за м²","vl":"","p":"square_meter","v":1271,"pu":"psm"},{"pl":"Общая площадь","vl":"","p":"size","v":36.5,"pu":"st","g":[{"gi":2,"gl":"О квартире","go":2,"po":10},{"gi":1,"go":1,"po":20}]},{"pl":"Жилая площадь","vl":"","p":"size_living_space","v":19.3,"pu":"sls","g":[{"gi":2,"gl":"О квартире","go":2,"po":15},{"gi":1,"go":1,"po":25}]},{"pl":"Площадь кухни","vl":"","p":"size_kitchen","v":7.1,"pu":"skt","g":[{"gi":2,"gl":"О квартире","go":2,"po":20},{"gi":1,"go":1,"po":30}]},{"pl":"Санузел","vl":"Раздельный","p":"bathroom","v":"1","pu":"bth","g":[{"gi":2,"gl":"О квартире","go":2,"po":25}]},{"pl":"Балкон","vl":"Лоджия","p":"balcony","v":"3","pu":"blc","g":[{"gi":2,"gl":"О квартире","go":2,"po":50}]},{"pl":"Этаж","vl":["5"],"p":"floor","v":[5],"pu":"fl","g":[{"gi":2,"gl":"О квартире","go":2,"po":65},{"gi":1,"go":1,"po":5}]},{"pl":"Этажность дома","vl":"5","p":"re_number_floors","v":"5","pu":"nmfl","g":[{"gi":1,"go":1,"po":10},{"gi":3,"gl":"О доме","go":3,"po":10}]},{"pl":"Материал стен","vl":"Кирпичный","p":"house_type","v":"3","pu":"hst","g":[{"gi":3,"gl":"О доме","go":3,"po":15}]},{"pl":"Год постройки","vl":"1975","p":"year_built","v":1975,"pu":"yb","g":[{"gi":1,"go":1,"po":15},{"gi":3,"gl":"О доме","go":3,"po":1}]},{"pl":"Состояние","vl":"Вторичное","p":"condition","v":"1","pu":"cnd","g":[{"gi":2,"gl":"О квартире","go":2,"po":85}]},{"pl":"Номер и дата договора","vl":"","p":"re_contract","v":"232/2 от 06.06.2025","pu":"rctr","g":[{"gi":2,"gl":"О квартире","go":2,"po":90}]}],"body":"Подписывайтесь на наш instagram @ecrzby для удобного слежения за новыми актуальными объектами.\nПредлагается аккуратная однокомнатная квартира в центре города на улице Карбышева, расположенная в кирпичном доме 1975 года постройки. Квартира находится на пятом этаже пятиэтажного здания и имеет общую площадь 36,5 м2, из которых жилая площадь составляет 19,3 м2, а кухня — 7,1 м2. В квартире раздельный санузел и просторная лоджия.\nИнтерьер квартиры выполнен в аккуратном косметическом ремонте: входная дверь металлическая, окна — ПВХ, обои в светлых тонах, потолки натяжные и снежка, полы отделаны паркетом и линолеумом. Частично заменена сантехника. Жилая комната площадью 19,3 м2 оснащена нишей под кровать и имеет выход на лоджию, что добавляет удобства. Просторная кухня (7,1 м2) укомплектована новым кухонным гарнитуром и газовой плитой.\nКвартира находится в пешей доступности от улицы Советской, рядом расположены магазины, остановки общественного транспорта, кинотеатр, аптеки и другие важные объекты инфраструктуры. В доме предусмотрены парковочные места, домофон, подвал и огороженная территория. Это отличное предложение для инвестиций или для молодой семьи!\nЧУП \"Единый центр реализации жилья\". УНН Лицензия 02240/170 от 22.11.2007Договор 232/2 от 06.06.2025 года.","category":"1010","company_ad":true,"currency":"USD","images":[{"id":"0000","media_storage":"rms","path":"adim1/95f4932d-cb24-42ed-91d0-1901777df4b8.jpg","yams_storage":false},{"id":"0000","media_storage":"rms","path":"adim1/748d25c3-7fe3-4e81-ac17-1e5cf2aa8b5b.jpg","yams_storage":false},{"id":"0000","media_storage":"rms","path":"adim1/01ed304f-4ef5-4c6e-9b84-6b66eacc2253.jpg","yams_storage":false},{"id":"0000","media_storage":"rms","path":"adim1/5ab09a70-c10e-4779-87b5-24bd6b472b41.jpg","yams_storage":false},{"id":"0000","media_storage":"rms","path":"adim1/1e79f24f-2753-492b-94f0-d8cf40b98f6e.jpg","yams_storage":false},{"id":"0000","media_storage":"rms","path":"adim1/d258b459-a16a-4bf9-b9a0-6e8f7d168dcc.jpg","yams_storage":false},{"id":"0000","media_storage":"rms","path":"adim1/bf090536-4aae-4bbc-935f-40a94b6ebd00.jpg","yams_storage":false},{"id":"0000","media_storage":"rms","path":"adim1/191361c1-3869-4b65-b73b-6d1b387e44d5.jpg","yams_storage":false},{"id":"0000","media_storage":"rms","path":"adim1/a44d31dc-d3b7-4004-9506-a8d1b65c1586.jpg","yams_storage":false},{"id":"0000","media_storage":"rms","path":"adim1/15d24414-5baf-4451-8a04-f6ff7788c92a.jpg","yams_storage":false},{"id":"0000","media_storage":"rms","path":"adim1/24357ee7-fd94-4b2b-bc5f-c05d3da1e150.jpg","yams_storage":false},{"id":"0000","media_storage":"rms","path":"adim1/cd81c5be-73c4-4ddf-85f9-1748806cc54e.jpg","yams_storage":false},{"id":"0000","media_storage":"rms","path":"adim1/2fde205b-0cbd-4ef1-9560-234f2ea74fb4.jpg","yams_storage":false},{"id":"0000","media_storage":"rms","path":"adim1/db943275-4f00-49d6-ab87-724a8255a98f.jpg","yams_storage":false},{"id":"0000","media_storage":"rms","path":"adim1/9dac0c3e-3d07-4e7e-9e03-e6a27e6cfe6c.jpg","yams_storage":false}],"is_mine":false,"list_id":226108472,"list_time":"2025-09-04T12:18:53Z","message_id":"adid1020628968","paid_services":{"halva":false,"highlight":false,"polepos":false,"ribbons":null},"phone_hidden":false,"price_byn":"14149216","price_eur":"3919450","price_usd":"4640000","remuneration_type":"1","show_parameters":{"show_call":true,"show_chat":true,"show_import_link":true,"show_web_shop_link":true},"subject":"Брест, Карбышева ул., 1-комн.","type":"sell"}}
