{"result":{"account_id":"OmXpixAov_obYMrNTAx7YCQ","account_parameters":[{"pl":"Имя","vl":"","p":"name","v":"Ольга","pu":"nme"},{"pl":"Адрес","vl":"","p":"address","v":"Гоголя ул, 90, Брест, Брестская область","pu":"ad","g":[{"gi":4,"gl":"Местоположение","go":4,"po":1}]}],"ad_id":1027644027,"ad_link":"https://re.kufar.by/vi/1027644027","ad_parameters":[{"pl":"Тип оплаты","vl":"Цена","p":"remuneration_type","v":"1","pu":"rtr"},{"pl":"Товары с Куфар Оплатой","vl":"-","p":"safedeal_enabled","v":false,"pu":"sde"},{"pl":"Товары с Куфар Доставкой","vl":"-","p":"delivery_enabled","v":false,"pu":"dle"},{"pl":"Координаты","vl":["",""],"p":"coordinates","v":[23.709783,52.092282],"pu":"gbx"},{"pl":"Тип сделки","vl":"Продажа","p":"type","v":"sell","pu":"typ"},{"pl":"Категория","vl":"Квартиры","p":"category","v":1010,"pu":"cat"},{"pl":"Область","vl":"Брестская","p":"region","v":1,"pu":"rgn"},{"pl":"Город / Район","vl":"Брест","p":"area","v":"1","pu":"ar"},{"pl":"Количество комнат","vl":"1","p":"rooms","v":"1","pu":"rms","g":[{"gi":2,"gl":"О квартире","go":2,"po":1},{"gi":1,"go":1,"po":1}]},{"pl":"Цена за м²","vl":"","p":"square_meter","v":2692,"pu":"psm"},{"pl":"Общая площадь","vl":"","p":"size","v":39,"pu":"st","g":[{"gi":2,"gl":"О квартире","go":2,"po":10},{"gi":1,"go":1,"po":20}]},{"pl":"Площадь по СНБ","vl":"","p":"size_snb","v":39,"pu":"szsb"},{"pl":"Жилая площадь","vl":"30","p":"size_living_space","v":30,"pu":"sls","g":[{"gi":2,"gl":"О квартире","go":2,"po":15},{"gi":1,"go":1,"po":25}]},{"pl":"Площадь кухни","vl":"9","p":"size_kitchen","v":9,"pu":"skt","g":[{"gi":2,"gl":"О квартире","go":2,"po":20},{"gi":1,"go":1,"po":30}]},{"pl":"Санузел","vl":"Совмещенный","p":"bathroom","v":"2","pu":"bth","g":[{"gi":2,"gl":"О квартире","go":2,"po":25}]},{"pl":"Балкон","vl":"Лоджия","p":"balcony","v":"3","pu":"blc","g":[{"gi":2,"gl":"О квартире","go":2,"po":50}]},{"pl":"Высота потолков","vl":"от 2.5 м","p":"flat_ceiling_height","v":"1","pu":"flch","g":[{"gi":2,"gl":"О квартире","go":2,"po":55}]},{"pl":"Число уровней","vl":"1","p":"flat_storeys","v":"1","pu":"fstr","g":[{"gi":2,"gl":"О квартире","go":2,"po":67}]},{"pl":"Ремонт","vl":"Дизайнерский","p":"flat_repair","v":"10","pu":"flrp","g":[{"gi":2,"gl":"О квартире","go":2,"po":60}]},{"pl":"Этаж","vl":["7"],"p":"floor","v":[7],"pu":"fl","g":[{"gi":2,"gl":"О квартире","go":2,"po":65},{"gi":1,"go":1,"po":5}]},{"pl":"Этажность дома","vl":"10","p":"re_number_floors","v":"10","pu":"nmfl","g":[{"gi":1,"go":1,"po":10},{"gi":3,"gl":"О доме","go":3,"po":10}]},{"pl":"Год постройки","vl":"2022","p":"year_built","v":2022,"pu":"yb","g":[{"gi":1,"go":1,"po":15},{"gi":3,"gl":"О доме","go":3,"po":1}]},{"pl":"Окна выходят","vl":["На улицу"],"p":"flat_windows_side","v":[4],"pu":"fws","g":[{"gi":2,"gl":"О квартире","go":2,"po":70}]},{"pl":"В новостройке","vl":"Да","p":"flat_new_building","v":true,"pu":"nwbl","g":[{"gi":3,"gl":"О доме","go":3,"po":5}]},{"pl":"Состояние","vl":"Новое","p":"condition","v":"2","pu":"cnd","g":[{"gi":2,"gl":"О квартире","go":2,"po":85}]},{"pl":"Возможен обмен","vl":"Да","p":"possible_exchange","v":true,"pu":"pse"}],"body":"Квартира с дизайнерским ремонтом есть вся бытовая техника ","category":"1010","company_ad":false,"currency":"USD","images":[{"id":"0000","media_storage":"rms","path":"adim1/ff133688-3848-4301-b056-8c90f4b3dd73.jpg","yams_storage":false},{"id":"0000","media_storage":"rms","path":"adim1/139e51e5-d558-4e94-a596-db94433c5349.jpg","yams_storage":false},{"id":"0000","media_storage":"rms","path":"adim1/61bb3fd0-ff74-44c7-9287-6971d99c1863.jpg","yams_storage":false},{"id":"0000","media_storage":"rms","path":"adim1/132c5a97-cf12-4e44-815c-a07a1aa89522.jpg","yams_storage":false},{"id":"0000","media_storage":"rms","path":"adim1/90b9fd8c-adfc-448f-9492-09c78985c882.jpg","yams_storage":false},{"id":"0000","media_storage":"rms","path":"adim1/d50e8898-37a8-49d2-bfcb-c9b16dd3fe53.jpg","yams_storage":false},{"id":"0000","media_storage":"rms","path":"adim1/12406171-2b4e-4c40-af3a-b8fa6d25fb54.jpg","yams_storage":false},{"id":"0000","media_storage":"rms","path":"adim1/0c7d0fb1-7aba-44ca-baf7-98309eacfa82.jpg","yams_storage":false},{"id":"0000","media_storage":"rms","path":"adim1/b1f0cb2d-af7f-46f6-8093-c28bb95d881a.jpg","yams_storage":false},{"id":"0000","media_storage":"rms","path":"adim1/e53e9e0a-d359-4779-ad94-0444ab27f5e4.jpg","yams_storage":false},{"id":"0000","media_storage":"rms","path":"adim1/3af8ff36-82fd-4287-8900-218343022d26.jpg","yams_storage":false}],"is_mine":false,"list_id":230503617,"list_time":"2025-09-02T07:33:44Z","message_id":"adid1027644027","paid_services":{"halva":false,"highlight":false,"polepos":false,"ribbons":null},"phone_hidden":false,"price_byn":"32018700","price_eur":"8869446","price_usd":"10500000","remuneration_type":"1","show_parameters":{"show_call":true,"show_chat":true,"show_import_link":true,"show_web_shop_link":true},"subject":"Квартира в новом доме с дизайнерским ремонтом ","type":"sell"}}
