{"result":{"account_id":"Ot--S8pU6IUUkvhDH3BFLhE","account_parameters":[{"pl":"Юридический адрес/Адрес регистрации","vl":"","p":"company_address","v":"Брест, ул. Советская д. 95","pu":"ca"},{"pl":"Имя","vl":"","p":"name","v":"ЗАО ''Альфа-Актив''","pu":"nme"},{"pl":"УНП","vl":"","p":"vat_number","v":"290426827","pu":"vn"},{"pl":"Контактное лицо","vl":"","p":"contact_person","v":"Наталья Малец","pu":"cp"},{"pl":"Адрес","vl":"","p":"address","v":"Ленинский район, Брест, Брестская область","pu":"ad","g":[{"gi":4,"gl":"Местоположение","go":4,"po":1}]}],"ad_id":1012674807,"ad_link":"https://re.kufar.by/vi/1012674807","ad_parameters":[{"pl":"Тип оплаты","vl":"Цена","p":"remuneration_type","v":"1","pu":"rtr"},{"pl":"Товары с Куфар Оплатой","vl":"-","p":"safedeal_enabled","v":false,"pu":"sde"},{"pl":"Товары с Куфар Доставкой","vl":"-","p":"delivery_enabled","v":false,"pu":"dle"},{"pl":"Координаты","vl":["",""],"p":"coordinates","v":[23.666637,52.121959],"pu":"gbx"},{"pl":"Тип сделки","vl":"Продажа","p":"type","v":"sell","pu":"typ"},{"pl":"Категория","vl":"Квартиры","p":"category","v":1010,"pu":"cat"},{"pl":"Область","vl":"Брестская","p":"region","v":1,"pu":"rgn"},{"pl":"Город / Район","vl":"Брест","p":"area","v":"1","pu":"ar"},{"pl":"Количество комнат","vl":"3","p":"rooms","v":"3","pu":"rms","g":[{"gi":2,"gl":"О квартире","go":2,"po":1},{"gi":1,"go":1,"po":1}]},{"pl":"Цена за м²","vl":"","p":"square_meter","v":970,"pu":"psm"},{"pl":"Общая площадь","vl":"","p":"size","v":78.3,"pu":"st","g":[{"gi":2,"gl":"О квартире","go":2,"po":10},{"gi":1,"go":1,"po":20}]},{"pl":"Жилая площадь","vl":"","p":"size_living_space","v":43.3,"pu":"sls","g":[{"gi":2,"gl":"О квартире","go":2,"po":15},{"gi":1,"go":1,"po":25}]},{"pl":"Площадь кухни","vl":"","p":"size_kitchen","v":11.6,"pu":"skt","g":[{"gi":2,"gl":"О квартире","go":2,"po":20},{"gi":1,"go":1,"po":30}]},{"pl":"Санузел","vl":"Раздельный","p":"bathroom","v":"1","pu":"bth","g":[{"gi":2,"gl":"О квартире","go":2,"po":25}]},{"pl":"Балкон","vl":"Лоджия","p":"balcony","v":"3","pu":"blc","g":[{"gi":2,"gl":"О квартире","go":2,"po":50}]},{"pl":"Ремонт","vl":"Косметический","p":"flat_repair","v":"1","pu":"flrp","g":[{"gi":2,"gl":"О квартире","go":2,"po":60}]},{"pl":"Этаж","vl":["4"],"p":"floor","v":[4],"pu":"fl","g":[{"gi":2,"gl":"О квартире","go":2,"po":65},{"gi":1,"go":1,"po":5}]},{"pl":"Этажность дома","vl":"7","p":"re_number_floors","v":"7","pu":"nmfl","g":[{"gi":1,"go":1,"po":10},{"gi":3,"gl":"О доме","go":3,"po":10}]},{"pl":"Материал стен","vl":"Кирпичный","p":"house_type","v":"3","pu":"hst","g":[{"gi":3,"gl":"О доме","go":3,"po":15}]},{"pl":"Год постройки","vl":"2011","p":"year_built","v":2011,"pu":"yb","g":[{"gi":1,"go":1,"po":15},{"gi":3,"gl":"О доме","go":3,"po":1}]},{"pl":"Состояние","vl":"Вторичное","p":"condition","v":"1","pu":"cnd","g":[{"gi":2,"gl":"О квартире","go":2,"po":85}]},{"pl":"Номер и дата договора","vl":"","p":"re_contract","v":"250158 от 29.03.2025","pu":"rctr","g":[{"gi":2,"gl":"О квартире","go":2,"po":90}]}],"body":" 250158\nПриобретая данный объект ПОКУПАТЕЛЬ не платит комиссию агентству. 3- комнатная квартира, г. Брест, Лт. Рябцева ул., 2011 г.п., 4/7 кирпичный, 82,8/78,3/43,3/11,6 кв.м., с/у раздельный. Квартира в хорошем состоянии для комфортного проживания. ПВХ, полы ламинат, стены окрашены. Встроенная кухня с бытовой техникой. Чистый, ухоженный подъезд. Благоустроенный двор, облагороженная придомовая территория с обустроенной детской площадкой, со стоянкой для автомобилей. Район с развитой инфраструктурой, рядом с домом расположены: продовольственный магазин, аптека, школа, садик, магазин хозяйственных товаров. Хорошая транспортная развязка, в шаговой доступности остановка общественного транспорта. Отличный вид из окон. Возможен торг. Лот 250158 Договор  158/1 от 27.03.2025, ЗАО «Альфа-Актив», УНП , лицензия  02240/92 от 29.12.2005 на право осуществления деятельности по оказанию юридических услуг (риэлтерские услуги)","category":"1010","company_ad":true,"currency":"USD","images":[{"id":"0000","media_storage":"rms","path":"adim1/ad8e0d67-075a-434d-9c98-5fb7b5723d3a.jpg","yams_storage":false},{"id":"0000","media_storage":"rms","path":"adim1/58623d03-55f6-4dd4-bcae-0ba8a939a77f.jpg","yams_storage":false},{"id":"0000","media_storage":"rms","path":"adim1/7d28c178-574c-4e18-a968-1d4eada5d24a.jpg","yams_storage":false},{"id":"0000","media_storage":"rms","path":"adim1/266a2eb4-5b94-40d7-83f3-bc035caed1d9.jpg","yams_storage":false},{"id":"0000","media_storage":"rms","path":"adim1/f3ad0cb0-c1c7-41da-b543-14dba3690281.jpg","yams_storage":false},{"id":"0000","media_storage":"rms","path":"adim1/45d36aa4-3e4b-4ee7-a057-0584d70c01ee.jpg","yams_storage":false},{"id":"0000","media_storage":"rms","path":"adim1/3228ee49-07a2-4a99-82f1-b1a6cf51ce35.jpg","yams_storage":false},{"id":"0000","media_storage":"rms","path":"adim1/03f3d500-ca6e-4647-a379-a42907aacf4c.jpg","yams_storage":false},{"id":"0000","media_storage":"rms","path":"adim1/5e411dfb-1031-4990-87c8-b8835f934f1d.jpg","yams_storage":false},{"id":"0000","media_storage":"rms","path":"adim1/f5eb6675-494b-4c91-8561-f6989b2f2dc1.jpg","yams_storage":false},{"id":"0000","media_storage":"rms","path":"adim1/cca6abf0-1ed1-44ac-9ec3-d454b70c5e31.jpg","yams_storage":false},{"id":"0000","media_storage":"rms","path":"adim1/4a290937-5d76-40f7-a3ec-234f977c548c.jpg","yams_storage":false},{"id":"0000","media_storage":"rms","path":"adim1/48ba6188-4de7-4ddf-8ba6-aae649268ec7.jpg","yams_storage":false},{"id":"0000","media_storage":"rms","path":"adim1/3acf2d56-97f5-4c0e-a2d9-d5023048ff58.jpg","yams_storage":false},{"id":"0000","media_storage":"rms","path":"adim1/1219d46d-7e2f-452c-9268-308a2ef694b6.jpg","yams_storage":false},{"id":"0000","media_storage":"rms","path":"adim1/2a3e99f3-e2fc-451d-9eee-8c6667dfb2ca.jpg","yams_storage":false},{"id":"0000","media_storage":"rms","path":"adim1/c356e57b-ba52-427c-91ff-6f154e169c74.jpg","yams_storage":false},{"id":"0000","media_storage":"rms","path":"adim1/aae7294b-05a0-447f-949d-f7e9ed6616f4.jpg","yams_storage":false},{"id":"0000","media_storage":"rms","path":"adim1/b8795339-41dc-4708-8966-d6fd3773ca2e.jpg","yams_storage":false},{"id":"0000","media_storage":"rms","path":"adim1/12f8bc05-700a-460a-a3b0-bc9d6710f7a8.jpg","yams_storage":false},{"id":"0000","media_storage":"rms","path":"adim1/cbe6e829-907c-435c-8126-4ecbc5032117.jpg","yams_storage":false},{"id":"0000","media_storage":"rms","path":"adim1/0dfe6335-edbd-49f3-a10e-c7305c2bbb38.jpg","yams_storage":false},{"id":"0000","media_storage":"rms","path":"adim1/14fff9d7-b857-45a7-810b-a78aff4b7899.jpg","yams_storage":false},{"id":"0000","media_storage":"rms","path":"adim1/feed3305-88b0-4546-b677-d2cc0e6bf59b.jpg","yams_storage":false},{"id":"0000","media_storage":"rms","path":"adim1/e375ca69-8458-475a-bece-c485ac3813cf.jpg","yams_storage":false},{"id":"0000","media_storage":"rms","path":"adim1/23344699-fca5-43b2-ac4d-499bd0e10764.jpg","yams_storage":false},{"id":"0000","media_storage":"rms","path":"adim1/91a6c57f-b640-4618-a4f4-1edad620b1cb.jpg","yams_storage":false},{"id":"0000","media_storage":"rms","path":"adim1/fa59096d-b85b-4206-9502-1287de8f3541.jpg","yams_storage":false},{"id":"0000","media_storage":"rms","path":"adim1/9b147885-7dd2-4aaa-b4b8-bcaf4a7b02a1.jpg","yams_storage":false}],"is_mine":false,"list_id":220515778,"list_time":"2025-09-10T12:38:34Z","message_id":"adid1012674807","paid_services":{"halva":false,"highlight":false,"polepos":false,"ribbons":null},"phone_hidden":false,"price_byn":"23175440","price_eur":"6419789","price_usd":"7600000","remuneration_type":"1","show_parameters":{"show_call":true,"show_chat":true,"show_import_link":true,"show_web_shop_link":true},"subject":"Брест, Советская ул., 3-комн.","type":"sell"}}
