{"result":{"account_id":"OnBRUnux9DyqZebyMD8x5ho","account_parameters":[{"pl":"Посмотреть это объявление на сайте продавца","vl":"","p":"import_link","v":"http://ecrz.by/realty/flats/3860805/","pu":"il"},{"pl":"УНП","vl":"","p":"vat_number","v":"290482452","pu":"vn"},{"pl":"Контактное лицо","vl":"","p":"contact_person","v":"Мария","pu":"cp"},{"pl":"Имя","vl":"","p":"name","v":"Единый Центр Реализации Жилья","pu":"nme"},{"pl":"Юридический адрес/Адрес регистрации","vl":"","p":"company_address","v":"г. Брест ул. Гоголя 2, каб.1","pu":"ca"},{"pl":"Адрес","vl":"","p":"address","v":"Бауманская ул, Брест, Брестская область","pu":"ad","g":[{"gi":4,"gl":"Местоположение","go":4,"po":1}]}],"ad_id":1030953669,"ad_link":"https://re.kufar.by/vi/1030953669","ad_parameters":[{"pl":"Товары с Куфар Доставкой","vl":"-","p":"delivery_enabled","v":false,"pu":"dle"},{"pl":"Координаты","vl":["",""],"p":"coordinates","v":[23.643218,52.11291],"pu":"gbx"},{"pl":"Тип оплаты","vl":"Цена","p":"remuneration_type","v":"1","pu":"rtr"},{"pl":"Тип сделки","vl":"Продажа","p":"type","v":"sell","pu":"typ"},{"pl":"Товары с Куфар Оплатой","vl":"-","p":"safedeal_enabled","v":false,"pu":"sde"},{"pl":"Категория","vl":"Квартиры","p":"category","v":1010,"pu":"cat"},{"pl":"Область","vl":"Брестская","p":"region","v":1,"pu":"rgn"},{"pl":"Город / Район","vl":"Брест","p":"area","v":"1","pu":"ar"},{"pl":"Количество комнат","vl":"1","p":"rooms","v":"1","pu":"rms","g":[{"gi":2,"gl":"О квартире","go":2,"po":1},{"gi":1,"go":1,"po":1}]},{"pl":"Цена за м²","vl":"","p":"square_meter","v":1211,"pu":"psm"},{"pl":"Общая площадь","vl":"","p":"size","v":28.9,"pu":"st","g":[{"gi":2,"gl":"О квартире","go":2,"po":10},{"gi":1,"go":1,"po":20}]},{"pl":"Жилая площадь","vl":"","p":"size_living_space","v":17,"pu":"sls","g":[{"gi":2,"gl":"О квартире","go":2,"po":15},{"gi":1,"go":1,"po":25}]},{"pl":"Площадь кухни","vl":"","p":"size_kitchen","v":5.12,"pu":"skt","g":[{"gi":2,"gl":"О квартире","go":2,"po":20},{"gi":1,"go":1,"po":30}]},{"pl":"Санузел","vl":"Совмещенный","p":"bathroom","v":"2","pu":"bth","g":[{"gi":2,"gl":"О квартире","go":2,"po":25}]},{"pl":"Балкон","vl":"Нет","p":"balcony","v":"2","pu":"blc","g":[{"gi":2,"gl":"О квартире","go":2,"po":50}]},{"pl":"Этаж","vl":["2"],"p":"floor","v":[2],"pu":"fl","g":[{"gi":2,"gl":"О квартире","go":2,"po":65},{"gi":1,"go":1,"po":5}]},{"pl":"Этажность дома","vl":"5","p":"re_number_floors","v":"5","pu":"nmfl","g":[{"gi":1,"go":1,"po":10},{"gi":3,"gl":"О доме","go":3,"po":10}]},{"pl":"Материал стен","vl":"Кирпичный","p":"house_type","v":"3","pu":"hst","g":[{"gi":3,"gl":"О доме","go":3,"po":15}]},{"pl":"Год постройки","vl":"1975","p":"year_built","v":1975,"pu":"yb","g":[{"gi":1,"go":1,"po":15},{"gi":3,"gl":"О доме","go":3,"po":1}]},{"pl":"Состояние","vl":"Вторичное","p":"condition","v":"1","pu":"cnd","g":[{"gi":2,"gl":"О квартире","go":2,"po":85}]},{"pl":"Номер и дата договора","vl":"","p":"re_contract","v":"с от 22.08.2025","pu":"rctr","g":[{"gi":2,"gl":"О квартире","go":2,"po":90}]}],"body":"Подписывайтесь на наш instagram @ecrzby для удобного слежения за новыми актуальными объектами.\nПродается 1-комнатная квартира в районе Речица по улице Бауманская, 1975 года постройки. Квартира расположена на втором этаже пятиэтажного кирпичного дома. Общая площадь составляет 28,9 м2, жилая — 17 м2, кухня — 5,12 м2. В квартире совмещенный санузел. \nПомещение с хорошим современным ремонтом в светлых тонах, выполнена замена электрики и сантехники. Входная дверь металлическая, окна ПВХ, полы покрыты ламинатом и плиткой, стены отделаны обоями, потолки натяжные. Санузел облицован плиткой. Из жилой комнаты имеется выход на цветник. Квартира теплая и не угловая.\nПри продаже остаются кухонный гарнитур, газовая плита Gefest, встроенный вместительный шкаф-купе и кровать. Микроволновая печь и стиральная машина могут быть оставлены по договоренности. \nВ шаговой доступности находятся остановки общественного транспорта, детский сад и магазин за домом. В непосредственной близости расположены рынок, Wilbderries и Ozon.\nЧУП \"Единый центр реализации жилья\". УНН  Лицензия 02240/170 от 22.11.2007 Договор 349/2 от 22.08.2025 года","category":"1010","company_ad":true,"currency":"USD","images":[{"id":"0000","media_storage":"rms","path":"adim1/1d60fcda-4bb5-4754-b558-e281f36ef7fb.jpg","yams_storage":false},{"id":"0000","media_storage":"rms","path":"adim1/49fd857b-fffc-4a28-9660-14467bf7ec05.jpg","yams_storage":false},{"id":"0000","media_storage":"rms","path":"adim1/80c3f205-31e2-491d-983a-6c4a643c111c.jpg","yams_storage":false},{"id":"0000","media_storage":"rms","path":"adim1/14d0ca5c-5056-46bb-b773-ec80a7c87a83.jpg","yams_storage":false},{"id":"0000","media_storage":"rms","path":"adim1/654c8cf5-9804-45fd-a9a2-c6520596ea57.jpg","yams_storage":false},{"id":"0000","media_storage":"rms","path":"adim1/eb831cba-48f0-4588-bab5-50b0dfa18efa.jpg","yams_storage":false},{"id":"0000","media_storage":"rms","path":"adim1/9aa247e5-8bc6-4d30-b474-ad6936671015.jpg","yams_storage":false},{"id":"0000","media_storage":"rms","path":"adim1/e32f5918-b830-4360-8912-443cb7e5515b.jpg","yams_storage":false},{"id":"0000","media_storage":"rms","path":"adim1/683e7cf3-974e-4402-babd-4e3b8c35a715.jpg","yams_storage":false},{"id":"0000","media_storage":"rms","path":"adim1/c383fc22-63fd-4212-9184-6e7739d75711.jpg","yams_storage":false},{"id":"0000","media_storage":"rms","path":"adim1/b7fdc033-3594-4813-9425-6766bd80f63f.jpg","yams_storage":false}],"is_mine":false,"list_id":232440279,"list_time":"2025-08-23T03:15:16Z","message_id":"adid1030953669","paid_services":{"halva":false,"highlight":false,"polepos":false,"ribbons":null},"phone_hidden":false,"price_byn":"10672900","price_eur":"2956482","price_usd":"3500000","remuneration_type":"1","show_parameters":{"show_call":true,"show_chat":true,"show_import_link":true,"show_web_shop_link":true},"subject":"Брест, Бауманская ул., 1-комн.","type":"sell"}}
