{"result":{"account_id":"OohCPsjA2X2SV-sHyyv39ro","account_parameters":[{"pl":"Имя","vl":"","p":"name","v":"ООО ''АН РИАЛИТИ''","pu":"nme"},{"pl":"УНП","vl":"","p":"vat_number","v":"291267309","pu":"vn"},{"pl":"Юридический адрес/Адрес регистрации","vl":"","p":"company_address","v":"Советская, 80-24","pu":"ca"},{"pl":"Контактное лицо","vl":"","p":"contact_person","v":"Людмила","pu":"cp"},{"pl":"Адрес","vl":"","p":"address","v":"Октябрьской Революции ул, Брест, Брестская область","pu":"ad","g":[{"gi":4,"gl":"Местоположение","go":4,"po":1}]}],"ad_id":1032538736,"ad_link":"https://re.kufar.by/vi/1032538736","ad_parameters":[{"pl":"Тип оплаты","vl":"Цена","p":"remuneration_type","v":"1","pu":"rtr"},{"pl":"Координаты","vl":["",""],"p":"coordinates","v":[23.788942,52.081329],"pu":"gbx"},{"pl":"Компания","vl":"","p":"trademark","v":"Агентство недвижимости ''РИАЛИТИ''","pu":"trd"},{"pl":"Тип сделки","vl":"Продажа","p":"type","v":"sell","pu":"typ"},{"pl":"Категория","vl":"Квартиры","p":"category","v":1010,"pu":"cat"},{"pl":"Область","vl":"Брестская","p":"region","v":1,"pu":"rgn"},{"pl":"Город / Район","vl":"Брест","p":"area","v":"1","pu":"ar"},{"pl":"Количество комнат","vl":"1","p":"rooms","v":"1","pu":"rms","g":[{"gi":2,"gl":"О квартире","go":2,"po":1},{"gi":1,"go":1,"po":1}]},{"pl":"Цена за м²","vl":"","p":"square_meter","v":3999.99,"pu":"psm"},{"pl":"Общая площадь","vl":"","p":"size","v":35.2,"pu":"st","g":[{"gi":2,"gl":"О квартире","go":2,"po":10},{"gi":1,"go":1,"po":20}]},{"pl":"Жилая площадь","vl":"","p":"size_living_space","v":13.7,"pu":"sls","g":[{"gi":2,"gl":"О квартире","go":2,"po":15},{"gi":1,"go":1,"po":25}]},{"pl":"Санузел","vl":"Совмещенный","p":"bathroom","v":"2","pu":"bth","g":[{"gi":2,"gl":"О квартире","go":2,"po":25}]},{"pl":"Балкон","vl":"Лоджия","p":"balcony","v":"3","pu":"blc","g":[{"gi":2,"gl":"О квартире","go":2,"po":50}]},{"pl":"Высота потолков","vl":"от 2.7 м","p":"flat_ceiling_height","v":"5","pu":"flch","g":[{"gi":2,"gl":"О квартире","go":2,"po":55}]},{"pl":"Этаж","vl":["9"],"p":"floor","v":[9],"pu":"fl","g":[{"gi":2,"gl":"О квартире","go":2,"po":65},{"gi":1,"go":1,"po":5}]},{"pl":"Материал стен","vl":"Монолитный","p":"house_type","v":"2","pu":"hst","g":[{"gi":3,"gl":"О доме","go":3,"po":15}]},{"pl":"Состояние","vl":"Вторичное","p":"condition","v":"1","pu":"cnd","g":[{"gi":2,"gl":"О квартире","go":2,"po":85}]},{"pl":"Номер и дата договора","vl":"","p":"re_contract","v":"№27624 от 25.10.2024","pu":"rctr","g":[{"gi":2,"gl":"О квартире","go":2,"po":90}]}],"body":"Предлагаем Вашему вниманию однокомнатные квартиры в строящемся жилом комплексе «Чайка» по улице Октябрьской революции!\nЦены от застройщика! Квартиры предлагаются без  отделки, выполняется стяжкка пола и штукатурка. Устанавливаются оконные блоки из ПВХ-профиля , входная дверь- деревянная, из сантехники-унитаз. Разводка электрики с установкой розеток и выключателей, подводка оптоволокна. Установка счетчиков воды, тепла и электроэнергии. Разводка отопления, монтаж радиаторов.\nПодъезды жилой части являются сквозными с возможностью выхода в дворовую территорию. Дворовая территория - \"двор без машин\"\nУдобное месторасположение: рядом остановки общественного транспорта, магазины, рынок, школа, детский сад, хорошая транспортная развязка.\nВозможен как наличный расчет, так и кредитование на выгодных условиях у банков-партнеров.\nЗаявленный срок сдачи дома – август 2026 года.\nЗвоните !Осталось всего несколько вариантов, не упустите свой шанс!\nДоговор 276 /2 от 25 .10.2024.\nЛицензия 02240/269 выдана МЮ РБ от 21 марта 2014 года.","category":"1010","company_ad":true,"currency":"BYR","images":[{"id":"0000","media_storage":"rms","path":"adim1/1eb92800-cbf4-494c-9a5b-6b4c9af00c96.jpg","yams_storage":false},{"id":"0000","media_storage":"rms","path":"adim1/2ae68b01-4bd2-4014-89ec-40edc40b1663.jpg","yams_storage":false}],"is_mine":false,"list_id":233410545,"list_time":"2025-09-16T17:08:56Z","message_id":"adid1032538736","paid_services":{"halva":false,"highlight":false,"polepos":false,"ribbons":null},"phone_hidden":false,"price_byn":"14080000","price_eur":"3900277","price_usd":"4617302","remuneration_type":"1","show_parameters":{"show_call":true,"show_chat":true,"show_import_link":true,"show_web_shop_link":true},"subject":"Продажа 1-комнатной квартиры","type":"sell"}}
