{"result":{"account_id":"OiguBxfYOWCNMTCYFjVqWX8","account_parameters":[{"pl":"Имя","vl":"","p":"name","v":"ООО ''АН РИАЛИТИ''","pu":"nme"},{"pl":"Контактное лицо","vl":"","p":"contact_person","v":"НАТАЛЬЯ","pu":"cp"},{"pl":"УНП","vl":"","p":"vat_number","v":"291267309","pu":"vn"},{"pl":"Юридический адрес/Адрес регистрации","vl":"","p":"company_address","v":"Советская, 80-24","pu":"ca"},{"pl":"Адрес","vl":"","p":"address","v":"Морозова ул, Брест, Брестская область","pu":"ad","g":[{"gi":4,"gl":"Местоположение","go":4,"po":1}]}],"ad_id":1031041735,"ad_link":"https://re.kufar.by/vi/1031041735","ad_parameters":[{"pl":"Тип оплаты","vl":"Цена","p":"remuneration_type","v":"1","pu":"rtr"},{"pl":"Товары с Куфар Доставкой","vl":"-","p":"delivery_enabled","v":false,"pu":"dle"},{"pl":"Тип сделки","vl":"Продажа","p":"type","v":"sell","pu":"typ"},{"pl":"Компания","vl":"","p":"trademark","v":"Агентство недвижимости ''РИАЛИТИ''","pu":"trd"},{"pl":"Товары с Куфар Оплатой","vl":"-","p":"safedeal_enabled","v":false,"pu":"sde"},{"pl":"Координаты","vl":["",""],"p":"coordinates","v":[23.72624,52.076569],"pu":"gbx"},{"pl":"Категория","vl":"Квартиры","p":"category","v":1010,"pu":"cat"},{"pl":"Область","vl":"Брестская","p":"region","v":1,"pu":"rgn"},{"pl":"Город / Район","vl":"Брест","p":"area","v":"1","pu":"ar"},{"pl":"Количество комнат","vl":"1","p":"rooms","v":"1","pu":"rms","g":[{"gi":2,"gl":"О квартире","go":2,"po":1},{"gi":1,"go":1,"po":1}]},{"pl":"Цена за м²","vl":"","p":"square_meter","v":1485,"pu":"psm"},{"pl":"Общая площадь","vl":"","p":"size","v":41.4,"pu":"st","g":[{"gi":2,"gl":"О квартире","go":2,"po":10},{"gi":1,"go":1,"po":20}]},{"pl":"Жилая площадь","vl":"","p":"size_living_space","v":18.1,"pu":"sls","g":[{"gi":2,"gl":"О квартире","go":2,"po":15},{"gi":1,"go":1,"po":25}]},{"pl":"Площадь кухни","vl":"","p":"size_kitchen","v":10.4,"pu":"skt","g":[{"gi":2,"gl":"О квартире","go":2,"po":20},{"gi":1,"go":1,"po":30}]},{"pl":"Санузел","vl":"Раздельный","p":"bathroom","v":"1","pu":"bth","g":[{"gi":2,"gl":"О квартире","go":2,"po":25}]},{"pl":"Балкон","vl":"Есть","p":"balcony","v":"1","pu":"blc","g":[{"gi":2,"gl":"О квартире","go":2,"po":50}]},{"pl":"Ремонт","vl":"Косметический","p":"flat_repair","v":"1","pu":"flrp","g":[{"gi":2,"gl":"О квартире","go":2,"po":60}]},{"pl":"Этаж","vl":["1"],"p":"floor","v":[1],"pu":"fl","g":[{"gi":2,"gl":"О квартире","go":2,"po":65},{"gi":1,"go":1,"po":5}]},{"pl":"Этажность дома","vl":"15","p":"re_number_floors","v":"15","pu":"nmfl","g":[{"gi":1,"go":1,"po":10},{"gi":3,"gl":"О доме","go":3,"po":10}]},{"pl":"Материал стен","vl":"Кирпичный","p":"house_type","v":"3","pu":"hst","g":[{"gi":3,"gl":"О доме","go":3,"po":15}]},{"pl":"Год постройки","vl":"2019","p":"year_built","v":2019,"pu":"yb","g":[{"gi":1,"go":1,"po":15},{"gi":3,"gl":"О доме","go":3,"po":1}]},{"pl":"Состояние","vl":"Вторичное","p":"condition","v":"1","pu":"cnd","g":[{"gi":2,"gl":"О квартире","go":2,"po":85}]},{"pl":"Номер и дата договора","vl":"","p":"re_contract","v":"№00725 от 10.01.2025","pu":"rctr","g":[{"gi":2,"gl":"О квартире","go":2,"po":90}]}],"body":"Покупая этот объект, ПОКУПАТЕЛЬ не платит агентству комиссию. \nПродается просторная 1-но комнатная квартира по ул. Морозова 2019 г. п. 1/15 этажного кирпичного дома.   Общая площадь по СНБ – 41,4 кв. м, общая – 38,2 кв. м., жилая- 18,1 кв. м, кухня – 10,4 кв. м. с раздельным санузлом и застекленным балконом.\nВ квартире выполнен свежий косметический ремонт: окна ПВХ, полы ламинат, стены оклеены обоями, потолки натяжные, в санузле стены окрашены, входная дверь металлическая (ЮРКАС). \nАккуратный и чистый подъезд, хорошие соседи, благоустроенный двор с детской игровой площадкой и парковкой для автомобилей. Удобное месторасположение: рядом остановки общественного транспорта, магазины, школа, детский сад, хорошая транспортная развязка.\n Код объекта 00725\nДоговор 007/2 от 10.01.2025г.\nЛицензия 02240/269 выдана МЮ РБ от 21 марта 2014 года.","category":"1010","company_ad":true,"currency":"USD","images":[{"id":"0000","media_storage":"rms","path":"adim1/0a8ea1ae-fd30-45a4-b543-83215d867171.jpg","yams_storage":false},{"id":"0000","media_storage":"rms","path":"adim1/8703c880-1543-4644-b314-def39ed74460.jpg","yams_storage":false},{"id":"0000","media_storage":"rms","path":"adim1/7eaa6d88-c463-4f51-b3a3-567c95e50c76.jpg","yams_storage":false},{"id":"0000","media_storage":"rms","path":"adim1/48c55503-f5d3-472f-8051-dc25f239ca69.jpg","yams_storage":false},{"id":"0000","media_storage":"rms","path":"adim1/4737a32e-db2b-4cbb-bf17-3e37164c4f09.jpg","yams_storage":false},{"id":"0000","media_storage":"rms","path":"adim1/44f82c06-9e61-40bd-b33f-799f05d23c87.jpg","yams_storage":false},{"id":"0000","media_storage":"rms","path":"adim1/25cf03db-006d-4c36-88ff-1a1333782fb6.jpg","yams_storage":false},{"id":"0000","media_storage":"rms","path":"adim1/d4bd6f0c-f5a5-4b7b-a1c1-749acbbe930f.jpg","yams_storage":false},{"id":"0000","media_storage":"rms","path":"adim1/3eca51b6-ed7f-4f66-b342-218ae3c45325.jpg","yams_storage":false},{"id":"0000","media_storage":"rms","path":"adim1/9f99c983-b258-4d11-b3ac-ba440c354631.jpg","yams_storage":false},{"id":"0000","media_storage":"rms","path":"adim1/6f720d62-0fe9-4fd3-9784-5d75470427d5.jpg","yams_storage":false},{"id":"0000","media_storage":"rms","path":"adim1/ee29d4a6-6434-4f15-9cda-c8879e48487b.jpg","yams_storage":false},{"id":"0000","media_storage":"rms","path":"adim1/203f89f3-920a-442c-aeab-45526bea915e.jpg","yams_storage":false},{"id":"0000","media_storage":"rms","path":"adim1/000cc25e-5dd6-410d-ad63-16db14b9d70a.jpg","yams_storage":false},{"id":"0000","media_storage":"rms","path":"adim1/c366a780-7b69-4cb7-a409-ad44c66b9178.jpg","yams_storage":false},{"id":"0000","media_storage":"rms","path":"adim1/7fb4bd62-bd7c-451d-a6b0-3baf76fec62f.jpg","yams_storage":false},{"id":"0000","media_storage":"rms","path":"adim1/f2f0a293-2c31-415a-bba1-9ac049fa4096.jpg","yams_storage":false}],"is_mine":false,"list_id":232498252,"list_time":"2025-08-23T15:51:06Z","message_id":"adid1031041735","paid_services":{"halva":false,"highlight":false,"polepos":false,"ribbons":null},"phone_hidden":false,"price_byn":"18753810","price_eur":"5194961","price_usd":"6150000","remuneration_type":"1","show_parameters":{"show_call":true,"show_chat":true,"show_import_link":true,"show_web_shop_link":true},"subject":"Продажа 1-комнатной квартиры","type":"sell"}}
