{"result":{"account_id":"OtEhJDE-kqOnnVjI2NZ0bkU","account_parameters":[{"pl":"Контактное лицо","vl":"","p":"contact_person","v":"Мария","pu":"cp"},{"pl":"Посмотреть это объявление на сайте продавца","vl":"","p":"import_link","v":"https://magazinkvartir.by/predlozhenija/kvartiry-i-komnaty/1-komnatnaya-kvartira-v-novostroyke-po-ul-ekelchika-v-g-breste-kod-25037-4186/","pu":"il"},{"pl":"Юридический адрес/Адрес регистрации","vl":"","p":"company_address","v":"224005, г. Брест, ул. Комсомольская, д.23/1","pu":"ca"},{"pl":"УНП","vl":"","p":"vat_number","v":"291513872","pu":"vn"},{"pl":"Имя","vl":"","p":"name","v":"Частное предприятие АН Магазин квартир","pu":"nme"},{"pl":"Данные о лицензии","vl":"","p":"company_number","v":"№ 02240/356, МЮ РБ, 6 февраля 2018 г.","pu":"cn"},{"pl":"Адрес","vl":"","p":"address","v":"Екельчика ул, Брест, Брестская область","pu":"ad","g":[{"gi":4,"gl":"Местоположение","go":4,"po":1}]}],"ad_id":1008344140,"ad_link":"https://re.kufar.by/vi/1008344140","ad_parameters":[{"pl":"Тип сделки","vl":"Продажа","p":"type","v":"sell","pu":"typ"},{"pl":"Товары с Куфар Оплатой","vl":"-","p":"safedeal_enabled","v":false,"pu":"sde"},{"pl":"Тип оплаты","vl":"Цена","p":"remuneration_type","v":"1","pu":"rtr"},{"pl":"Координаты","vl":["",""],"p":"coordinates","v":[23.708669,52.067287],"pu":"gbx"},{"pl":"Товары с Куфар Доставкой","vl":"-","p":"delivery_enabled","v":false,"pu":"dle"},{"pl":"Категория","vl":"Квартиры","p":"category","v":1010,"pu":"cat"},{"pl":"Область","vl":"Брестская","p":"region","v":1,"pu":"rgn"},{"pl":"Город / Район","vl":"Брест","p":"area","v":"1","pu":"ar"},{"pl":"Количество комнат","vl":"1","p":"rooms","v":"1","pu":"rms","g":[{"gi":2,"gl":"О квартире","go":2,"po":1},{"gi":1,"go":1,"po":1}]},{"pl":"Цена за м²","vl":"","p":"square_meter","v":1142,"pu":"psm"},{"pl":"Общая площадь","vl":"","p":"size","v":45.1,"pu":"st","g":[{"gi":2,"gl":"О квартире","go":2,"po":10},{"gi":1,"go":1,"po":20}]},{"pl":"Жилая площадь","vl":"","p":"size_living_space","v":17.1,"pu":"sls","g":[{"gi":2,"gl":"О квартире","go":2,"po":15},{"gi":1,"go":1,"po":25}]},{"pl":"Площадь кухни","vl":"11","p":"size_kitchen","v":11,"pu":"skt","g":[{"gi":2,"gl":"О квартире","go":2,"po":20},{"gi":1,"go":1,"po":30}]},{"pl":"Санузел","vl":"Раздельный","p":"bathroom","v":"1","pu":"bth","g":[{"gi":2,"gl":"О квартире","go":2,"po":25}]},{"pl":"Балкон","vl":"Лоджия","p":"balcony","v":"3","pu":"blc","g":[{"gi":2,"gl":"О квартире","go":2,"po":50}]},{"pl":"Этаж","vl":["1"],"p":"floor","v":[1],"pu":"fl","g":[{"gi":2,"gl":"О квартире","go":2,"po":65},{"gi":1,"go":1,"po":5}]},{"pl":"Этажность дома","vl":"8","p":"re_number_floors","v":"8","pu":"nmfl","g":[{"gi":1,"go":1,"po":10},{"gi":3,"gl":"О доме","go":3,"po":10}]},{"pl":"Материал стен","vl":"Панельный","p":"house_type","v":"1","pu":"hst","g":[{"gi":3,"gl":"О доме","go":3,"po":15}]},{"pl":"Год постройки","vl":"2024","p":"year_built","v":2024,"pu":"yb","g":[{"gi":1,"go":1,"po":15},{"gi":3,"gl":"О доме","go":3,"po":1}]},{"pl":"Состояние","vl":"Новое","p":"condition","v":"2","pu":"cnd","g":[{"gi":2,"gl":"О квартире","go":2,"po":85}]},{"pl":"Номер и дата договора","vl":"","p":"re_contract","v":"№ 37 от 18.02.2025г.","pu":"rctr","g":[{"gi":2,"gl":"О квартире","go":2,"po":90}]}],"body":"Предлагаем купить 1-комнатную квартиру в новостройке по ул. Екельчика в г. Бресте. Площадь: общая по СНБ 45,1 м2, жилая- 17,1 м2, кухня- 11,0 м2, панельный дом 2024 г.п., этаж 1/8, раздельный с/у, застекленная лоджия. Квартира под чистовую отделку. Отличная планировка, комната 17,1 м2, кухня-11,0 м2, просторный коридор 9,9 м2. Окна ПВХ, входная дверь металлическая. Улучшенной планировки подъезд. Отдельная зона парковки, во дворе оборудована детская площадка. Развита инфраструктура: магазин, д/сад (во дворе дома), школа, остановки общественного транспорта и т.п. Код объекта 25037. Договор № 37 от 18.02.2025г.","category":"1010","company_ad":true,"currency":"USD","images":[{"id":"0000","media_storage":"rms","path":"adim1/267931c7-cc02-43a4-b84e-5f44c857280e.jpg","yams_storage":false},{"id":"0000","media_storage":"rms","path":"adim1/03b665eb-d1df-41ba-896e-4dfbaf15747e.jpg","yams_storage":false},{"id":"0000","media_storage":"rms","path":"adim1/c732e897-de71-4f32-bf28-ed5e6fbec0c8.jpg","yams_storage":false},{"id":"0000","media_storage":"rms","path":"adim1/f6b76d39-7c52-4d0f-aaf4-e504e4f8cff6.jpg","yams_storage":false},{"id":"0000","media_storage":"rms","path":"adim1/54dd624e-0f23-4f0f-945a-05a6d6836777.jpg","yams_storage":false},{"id":"0000","media_storage":"rms","path":"adim1/ed5d8fd6-c674-4854-9070-c5ed70b33505.jpg","yams_storage":false},{"id":"0000","media_storage":"rms","path":"adim1/49c8d761-ca47-4978-be32-e408a05b43a6.jpg","yams_storage":false},{"id":"0000","media_storage":"rms","path":"adim1/328e63c4-04be-427d-8617-2417a864ca13.jpg","yams_storage":false},{"id":"0000","media_storage":"rms","path":"adim1/70f795cf-18b8-41b9-ada7-1d14c0d01963.jpg","yams_storage":false},{"id":"0000","media_storage":"rms","path":"adim1/ca59395e-5a64-4518-bb0f-ed45e08bff14.jpg","yams_storage":false},{"id":"0000","media_storage":"rms","path":"adim1/d17a3281-020b-4cf9-a09c-4218a2b19c07.jpg","yams_storage":false},{"id":"0000","media_storage":"rms","path":"adim1/2e11c41a-7819-4339-ba3c-941299c0617e.jpg","yams_storage":false},{"id":"0000","media_storage":"rms","path":"adim1/3ec5d40e-11b3-469a-ba01-d87c1ed42405.jpg","yams_storage":false},{"id":"0000","media_storage":"rms","path":"adim1/c665adc8-e4f6-4269-9218-8d652a1f7cb6.jpg","yams_storage":false}],"is_mine":false,"list_id":216917914,"list_time":"2025-06-26T09:08:08Z","message_id":"adid1008344140","paid_services":{"halva":false,"highlight":false,"polepos":false,"ribbons":null},"phone_hidden":false,"price_byn":"15704410","price_eur":"4350252","price_usd":"5150000","remuneration_type":"1","show_parameters":{"show_call":true,"show_chat":true,"show_import_link":true,"show_web_shop_link":true},"subject":"1-комнатная квартира в новостройке. Код 25037","type":"sell"}}
