{"result":{"account_id":"OtB9DDd0jlErFdRzjUOfotA","account_parameters":[{"pl":"УНП","vl":"","p":"vat_number","v":"290472700","pu":"vn"},{"pl":"Контактное лицо","vl":"","p":"contact_person","v":"Наталья","pu":"cp"},{"pl":"Юридический адрес/Адрес регистрации","vl":"","p":"company_address","v":"г. Брест, проспект Машерова, 30","pu":"ca"},{"pl":"Имя","vl":"","p":"name","v":"Гарант успеха","pu":"nme"},{"pl":"Посмотреть это объявление на сайте продавца","vl":"","p":"import_link","v":"https://garantus.by/catalog/apartment/lot-7261-brest-ul-moskovskaya-prodaza-4-komnatnoi-kvartiry-c36e82d8-8005-4797-87a0-903b9bb28ed0","pu":"il"},{"pl":"Адрес","vl":"","p":"address","v":"Московская ул, Брест, Брестская область","pu":"ad","g":[{"gi":4,"gl":"Местоположение","go":4,"po":1}]}],"ad_id":255106662,"ad_link":"https://re.kufar.by/vi/255106662","ad_parameters":[{"pl":"Координаты","vl":["",""],"p":"coordinates","v":[23.758052,52.098437],"pu":"gbx"},{"pl":"Тип оплаты","vl":"Цена","p":"remuneration_type","v":"1","pu":"rtr"},{"pl":"Тип сделки","vl":"Продажа","p":"type","v":"sell","pu":"typ"},{"pl":"Категория","vl":"Квартиры","p":"category","v":1010,"pu":"cat"},{"pl":"Область","vl":"Брестская","p":"region","v":1,"pu":"rgn"},{"pl":"Город / Район","vl":"Брест","p":"area","v":"1","pu":"ar"},{"pl":"Количество комнат","vl":"4","p":"rooms","v":"4","pu":"rms","g":[{"gi":2,"gl":"О квартире","go":2,"po":1},{"gi":1,"go":1,"po":1}]},{"pl":"Цена за м²","vl":"","p":"square_meter","v":871,"pu":"psm"},{"pl":"Общая площадь","vl":"","p":"size","v":58.5,"pu":"st","g":[{"gi":2,"gl":"О квартире","go":2,"po":10},{"gi":1,"go":1,"po":20}]},{"pl":"Жилая площадь","vl":"","p":"size_living_space","v":41.8,"pu":"sls","g":[{"gi":2,"gl":"О квартире","go":2,"po":15},{"gi":1,"go":1,"po":25}]},{"pl":"Площадь кухни","vl":"","p":"size_kitchen","v":5.4,"pu":"skt","g":[{"gi":2,"gl":"О квартире","go":2,"po":20},{"gi":1,"go":1,"po":30}]},{"pl":"Санузел","vl":"Совмещенный","p":"bathroom","v":"2","pu":"bth","g":[{"gi":2,"gl":"О квартире","go":2,"po":25}]},{"pl":"Балкон","vl":"Есть","p":"balcony","v":"1","pu":"blc","g":[{"gi":2,"gl":"О квартире","go":2,"po":50}]},{"pl":"Высота потолков","vl":"от 2.5 м","p":"flat_ceiling_height","v":"1","pu":"flch","g":[{"gi":2,"gl":"О квартире","go":2,"po":55}]},{"pl":"Этаж","vl":["5"],"p":"floor","v":[5],"pu":"fl","g":[{"gi":2,"gl":"О квартире","go":2,"po":65},{"gi":1,"go":1,"po":5}]},{"pl":"Этажность дома","vl":"5","p":"re_number_floors","v":"5","pu":"nmfl","g":[{"gi":1,"go":1,"po":10},{"gi":3,"gl":"О доме","go":3,"po":10}]},{"pl":"Материал стен","vl":"Панельный","p":"house_type","v":"1","pu":"hst","g":[{"gi":3,"gl":"О доме","go":3,"po":15}]},{"pl":"Год постройки","vl":"1973","p":"year_built","v":1973,"pu":"yb","g":[{"gi":1,"go":1,"po":15},{"gi":3,"gl":"О доме","go":3,"po":1}]},{"pl":"Состояние","vl":"Вторичное","p":"condition","v":"1","pu":"cnd","g":[{"gi":2,"gl":"О квартире","go":2,"po":85}]},{"pl":"Номер и дата договора","vl":"","p":"re_contract","v":"№12/2 от 04.07.2023","pu":"rctr","g":[{"gi":2,"gl":"О квартире","go":2,"po":90}]}],"body":"Лот 7261. В микрорайоне Восток продается уютная четырёхкомнатная квартира общей площадью 58,5 кв.м в панельном доме 1973 года постройки. В Квартире выполнена перепланировка (узаконена). Кухня объединена с комнатой, оборудовано спальное место, совмещенный санузел, функциональный коридор, балкон из зала.\n\nКвартира в аккуратном жилом состоянии. Окна ПВХ + дерево. Напольное покрытие - паркет и плитка. Потолок - снежка. Межкомнатные двери МДФ. Входная дверь - металлическая. В санузле плитка. При продаже остается встроенная кухня и три шкафа-купе.\n\nРядом с домом имеются парковочные места. Благоустроенная территория с детской площадкой.\nУдобная транспортная развязка. \n\nПо соседству находится несколько крупных торговых центров и магазинов. Развитая инфраструктура: школы, детские сады, парк Воинов-Интернационалистов, поликлиника, аптеки и другие социально значимые объекты.\n\nОстались вопросы? Звоните или пишите, указав номер лота.\nНаш инстаграм @garantuspeha. Подпишись, чтобы быть в курсе срочных продаж.\n\nПокупая квартиру с нами, вы будете уверены в безопасности и надежности сделки.\nПоможем продать Вашу квартиру для покупки этой. Звоните!\nЧУП «Гарант успеха», УНП , лицензия 02240/137 от 20.10.2006 г., договор на оказание риэлтерских услуг 12/2 от 04.07.2023 г.","category":"1010","company_ad":true,"currency":"USD","images":[{"id":"0000","media_storage":"rms","path":"adim1/8b21906c-a6d9-4e68-a3da-45c0dfd8632c.jpg","yams_storage":false},{"id":"0000","media_storage":"rms","path":"adim1/606362db-e8e2-4c32-90ea-567cd59b8af4.jpg","yams_storage":false},{"id":"0000","media_storage":"rms","path":"adim1/d700f5d9-59f0-4d60-9ea1-d0b9a47ac045.jpg","yams_storage":false},{"id":"0000","media_storage":"rms","path":"adim1/b78c69fc-7912-48f9-abc4-5ac43bf9a36f.jpg","yams_storage":false},{"id":"0000","media_storage":"rms","path":"adim1/352c1554-7897-41f7-9cf1-fdd7d58fb3a0.jpg","yams_storage":false},{"id":"0000","media_storage":"rms","path":"adim1/016be29c-0426-4c2a-845a-f3d5706c5422.jpg","yams_storage":false},{"id":"0000","media_storage":"rms","path":"adim1/2a087f9c-e5d5-4655-9b95-8fbb34c66c75.jpg","yams_storage":false},{"id":"0000","media_storage":"rms","path":"adim1/8e0d36e8-7c47-4151-9110-b9ba33ff073f.jpg","yams_storage":false},{"id":"0000","media_storage":"rms","path":"adim1/21bca85a-fd60-4c98-8ae7-76037a24216f.jpg","yams_storage":false},{"id":"0000","media_storage":"rms","path":"adim1/3f5c4099-f17b-4611-a35c-309f7d486e06.jpg","yams_storage":false},{"id":"0000","media_storage":"rms","path":"adim1/d485cbbd-9c1a-4e5d-bfa2-f55dd9820808.jpg","yams_storage":false},{"id":"0000","media_storage":"rms","path":"adim1/02d83de3-bd19-4f06-94d1-32a36b52cb04.jpg","yams_storage":false},{"id":"0000","media_storage":"rms","path":"adim1/9c349ff9-3b07-4ec9-91b4-6cf27c26edad.jpg","yams_storage":false},{"id":"0000","media_storage":"rms","path":"adim1/05c5b210-8f49-4684-b42b-4a7d6af6dfcd.jpg","yams_storage":false},{"id":"0000","media_storage":"rms","path":"adim1/160fb464-1ba0-4e60-b992-a650c953e6ff.jpg","yams_storage":false},{"id":"0000","media_storage":"rms","path":"adim1/c8c0f129-5c6f-434d-b15f-ae6685d2acd6.jpg","yams_storage":false},{"id":"0000","media_storage":"rms","path":"adim1/686e6c41-5c39-4c08-a6f5-45c687db8574.jpg","yams_storage":false}],"is_mine":false,"list_id":208300717,"list_time":"2025-06-24T06:06:07Z","message_id":"adid255106662","paid_services":{"halva":false,"highlight":false,"polepos":false,"ribbons":null},"phone_hidden":false,"price_byn":"15551940","price_eur":"4308017","price_usd":"5100000","remuneration_type":"1","show_parameters":{"show_call":true,"show_chat":true,"show_import_link":true,"show_web_shop_link":true},"subject":"Продажа 4-комнатной квартиры, ул. Московская","type":"sell"}}
