{"result":{"account_id":"Opt9SnMUU1yQq6pc1vTEqv8","account_parameters":[{"pl":"Контактное лицо","vl":"","p":"contact_person","v":"Мария","pu":"cp"},{"pl":"Юридический адрес/Адрес регистрации","vl":"","p":"company_address","v":"224005, г. Брест, ул. Комсомольская, д.23/1","pu":"ca"},{"pl":"Данные о лицензии","vl":"","p":"company_number","v":"№ 02240/356, МЮ РБ, 6 февраля 2018 г.","pu":"cn"},{"pl":"УНП","vl":"","p":"vat_number","v":"291513872","pu":"vn"},{"pl":"Посмотреть это объявление на сайте продавца","vl":"","p":"import_link","v":"https://magazinkvartir.by/predlozhenija/kvartiry-i-komnaty/1-komnatnaya-kvartira-v-tsentre-goroda-bresta-po-ulitse-gogolya-kod-24149-3966/","pu":"il"},{"pl":"Имя","vl":"","p":"name","v":"Частное предприятие АН Магазин квартир","pu":"nme"},{"pl":"Адрес","vl":"","p":"address","v":"Гоголя ул, Брест, Брестская область","pu":"ad","g":[{"gi":4,"gl":"Местоположение","go":4,"po":1}]}],"ad_id":239196709,"ad_link":"https://re.kufar.by/vi/239196709","ad_parameters":[{"pl":"Товары с Куфар Доставкой","vl":"-","p":"delivery_enabled","v":false,"pu":"dle"},{"pl":"Товары с Куфар Оплатой","vl":"-","p":"safedeal_enabled","v":false,"pu":"sde"},{"pl":"Тип оплаты","vl":"Цена","p":"remuneration_type","v":"1","pu":"rtr"},{"pl":"Координаты","vl":["",""],"p":"coordinates","v":[23.689841,52.09205],"pu":"gbx"},{"pl":"Тип сделки","vl":"Продажа","p":"type","v":"sell","pu":"typ"},{"pl":"Категория","vl":"Квартиры","p":"category","v":1010,"pu":"cat"},{"pl":"Область","vl":"Брестская","p":"region","v":1,"pu":"rgn"},{"pl":"Город / Район","vl":"Брест","p":"area","v":"1","pu":"ar"},{"pl":"Количество комнат","vl":"1","p":"rooms","v":"1","pu":"rms","g":[{"gi":2,"gl":"О квартире","go":2,"po":1},{"gi":1,"go":1,"po":1}]},{"pl":"Цена за м²","vl":"","p":"square_meter","v":1463,"pu":"psm"},{"pl":"Общая площадь","vl":"","p":"size","v":32.8,"pu":"st","g":[{"gi":2,"gl":"О квартире","go":2,"po":10},{"gi":1,"go":1,"po":20}]},{"pl":"Жилая площадь","vl":"","p":"size_living_space","v":17.6,"pu":"sls","g":[{"gi":2,"gl":"О квартире","go":2,"po":15},{"gi":1,"go":1,"po":25}]},{"pl":"Площадь кухни","vl":"","p":"size_kitchen","v":5.9,"pu":"skt","g":[{"gi":2,"gl":"О квартире","go":2,"po":20},{"gi":1,"go":1,"po":30}]},{"pl":"Санузел","vl":"Совмещенный","p":"bathroom","v":"2","pu":"bth","g":[{"gi":2,"gl":"О квартире","go":2,"po":25}]},{"pl":"Балкон","vl":"Есть","p":"balcony","v":"1","pu":"blc","g":[{"gi":2,"gl":"О квартире","go":2,"po":50}]},{"pl":"Этаж","vl":["2"],"p":"floor","v":[2],"pu":"fl","g":[{"gi":2,"gl":"О квартире","go":2,"po":65},{"gi":1,"go":1,"po":5}]},{"pl":"Этажность дома","vl":"5","p":"re_number_floors","v":"5","pu":"nmfl","g":[{"gi":1,"go":1,"po":10},{"gi":3,"gl":"О доме","go":3,"po":10}]},{"pl":"Материал стен","vl":"Кирпичный","p":"house_type","v":"3","pu":"hst","g":[{"gi":3,"gl":"О доме","go":3,"po":15}]},{"pl":"Год постройки","vl":"1962","p":"year_built","v":1962,"pu":"yb","g":[{"gi":1,"go":1,"po":15},{"gi":3,"gl":"О доме","go":3,"po":1}]},{"pl":"Состояние","vl":"Вторичное","p":"condition","v":"1","pu":"cnd","g":[{"gi":2,"gl":"О квартире","go":2,"po":85}]},{"pl":"Номер и дата договора","vl":"","p":"re_contract","v":"№ 149 от 20.06.2024 г.","pu":"rctr","g":[{"gi":2,"gl":"О квартире","go":2,"po":90}]}],"body":"Предлагаем купить 1-комнатную квартиру в Центре города Бреста по улице Гоголя. Квартира расположена на 2-ом этаже кирпичного 5- этажного дома, 1962 года постройки. Общая площадь квартиры составляет 32,8 м2, жилая площадь – 17,6 м2, кухня – 5,9 м2, санузел совмещённый. Застеклённый балкон. Квартира в жилом состоянии: входная дверь деревянная, пол- ламинат, потолки – натяжные/ сайдинг, в санузл и ванная комната облицованы керамической плиткой, установлены стеклопакеты. Встроенный кухонный гарнитур. В стоимость входит вся мебель и техника! Отличное месторасположение! В шаговой доступности: детские сады, школа, сквер, центральная пешеходная улица города Советская, всё необходимое для комфортного проживания. Код объекта 24149 ТОРГ ! Договор № 149 от 20.06.2024 г.\nЧастное предприятие \"АН Магазин квартир\"   Лицензия: № 02240/356, МЮ РБ, 6 февраля 2018 г.","category":"1010","company_ad":true,"currency":"USD","images":[{"id":"0000","media_storage":"rms","path":"adim1/00ad87ea-9a4c-46dd-ac6e-aadff932e299.jpg","yams_storage":false},{"id":"0000","media_storage":"rms","path":"adim1/6de7887b-02b5-41db-b0af-c799ad9fffad.jpg","yams_storage":false},{"id":"0000","media_storage":"rms","path":"adim1/5a5ebbbd-a113-4b79-aeac-a9e67229e595.jpg","yams_storage":false},{"id":"0000","media_storage":"rms","path":"adim1/e4c06226-5414-42fd-acbc-693bcc0be847.jpg","yams_storage":false},{"id":"0000","media_storage":"rms","path":"adim1/6e9f9c92-fc81-42a2-bdd8-6d9a2dc01671.jpg","yams_storage":false},{"id":"0000","media_storage":"rms","path":"adim1/54c91136-f62b-4884-8b99-bf554276359c.jpg","yams_storage":false},{"id":"0000","media_storage":"rms","path":"adim1/f9a00d9b-d186-4c96-8071-d8fdf9440dfd.jpg","yams_storage":false},{"id":"0000","media_storage":"rms","path":"adim1/8cc8c64c-d4cf-4144-9035-90dae6d61d60.jpg","yams_storage":false},{"id":"0000","media_storage":"rms","path":"adim1/9e3988ed-a151-46f7-b56e-329c8542d447.jpg","yams_storage":false},{"id":"0000","media_storage":"rms","path":"adim1/234da3fc-43c7-4fc3-9407-6a32a7c302a4.jpg","yams_storage":false},{"id":"0000","media_storage":"rms","path":"adim1/10e6ec6d-cc6d-407e-9bb2-e6c5b7319432.jpg","yams_storage":false},{"id":"0000","media_storage":"rms","path":"adim1/4bdca5f0-398a-44d5-8315-fe426a85dc00.jpg","yams_storage":false},{"id":"0000","media_storage":"rms","path":"adim1/6b0739ee-b813-4bbe-9209-3a0c50a61b50.jpg","yams_storage":false},{"id":"0000","media_storage":"rms","path":"adim1/20b3eba9-59b8-445c-b0bc-ee101d568090.jpg","yams_storage":false},{"id":"0000","media_storage":"rms","path":"adim1/818f1e42-6d28-4977-8467-d1fe829c03d8.jpg","yams_storage":false},{"id":"0000","media_storage":"rms","path":"adim1/d3573e8b-838b-407e-9a05-be931d944e20.jpg","yams_storage":false}],"is_mine":false,"list_id":198206046,"list_time":"2025-06-28T11:16:00Z","message_id":"adid239196709","paid_services":{"halva":false,"highlight":false,"polepos":false,"ribbons":null},"phone_hidden":false,"price_byn":"14637120","price_eur":"4054604","price_usd":"4800000","remuneration_type":"1","show_parameters":{"show_call":true,"show_chat":true,"show_import_link":true,"show_web_shop_link":true},"subject":"1-комнатная квартира в Центре. Код 24149","type":"sell"}}
