{"result":{"account_id":"OlT5xz7YcBwq1hx09x0Ntc4","account_parameters":[{"pl":"Юридический адрес/Адрес регистрации","vl":"","p":"company_address","v":"220116, г. Минск, пр-т Дзержинского, 104, оф. 602Б","pu":"ca"},{"pl":"Имя","vl":"","p":"name","v":"ООО Экспресснедвижимость-риэлт","pu":"nme"},{"pl":"УНП","vl":"","p":"vat_number","v":"193505113","pu":"vn"},{"pl":"Адрес","vl":"","p":"address","v":"Московская ул, Брест, Брестская область","pu":"ad","g":[{"gi":4,"gl":"Местоположение","go":4,"po":1}]}],"ad_id":245188207,"ad_link":"https://re.kufar.by/vi/245188207","ad_parameters":[{"pl":"Товары с Куфар Оплатой","vl":"-","p":"safedeal_enabled","v":false,"pu":"sde"},{"pl":"Координаты","vl":["",""],"p":"coordinates","v":[23.775297,52.102014],"pu":"gbx"},{"pl":"Тип оплаты","vl":"Цена","p":"remuneration_type","v":"1","pu":"rtr"},{"pl":"Тип сделки","vl":"Продажа","p":"type","v":"sell","pu":"typ"},{"pl":"Товары с Куфар Доставкой","vl":"-","p":"delivery_enabled","v":false,"pu":"dle"},{"pl":"Категория","vl":"Квартиры","p":"category","v":1010,"pu":"cat"},{"pl":"Область","vl":"Брестская","p":"region","v":1,"pu":"rgn"},{"pl":"Город / Район","vl":"Брест","p":"area","v":"1","pu":"ar"},{"pl":"Количество комнат","vl":"4","p":"rooms","v":"4","pu":"rms","g":[{"gi":2,"gl":"О квартире","go":2,"po":1},{"gi":1,"go":1,"po":1}]},{"pl":"Цена за м²","vl":"","p":"square_meter","v":877,"pu":"psm"},{"pl":"Общая площадь","vl":"","p":"size","v":104.9,"pu":"st","g":[{"gi":2,"gl":"О квартире","go":2,"po":10},{"gi":1,"go":1,"po":20}]},{"pl":"Жилая площадь","vl":"","p":"size_living_space","v":60.4,"pu":"sls","g":[{"gi":2,"gl":"О квартире","go":2,"po":15},{"gi":1,"go":1,"po":25}]},{"pl":"Площадь кухни","vl":"","p":"size_kitchen","v":13.8,"pu":"skt","g":[{"gi":2,"gl":"О квартире","go":2,"po":20},{"gi":1,"go":1,"po":30}]},{"pl":"Санузел","vl":"Два","p":"bathroom","v":"3","pu":"bth","g":[{"gi":2,"gl":"О квартире","go":2,"po":25}]},{"pl":"Балкон","vl":"Лоджия","p":"balcony","v":"3","pu":"blc","g":[{"gi":2,"gl":"О квартире","go":2,"po":50}]},{"pl":"Ремонт","vl":"Евро","p":"flat_repair","v":"5","pu":"flrp","g":[{"gi":2,"gl":"О квартире","go":2,"po":60}]},{"pl":"Этаж","vl":["5"],"p":"floor","v":[5],"pu":"fl","g":[{"gi":2,"gl":"О квартире","go":2,"po":65},{"gi":1,"go":1,"po":5}]},{"pl":"Этажность дома","vl":"5","p":"re_number_floors","v":"5","pu":"nmfl","g":[{"gi":1,"go":1,"po":10},{"gi":3,"gl":"О доме","go":3,"po":10}]},{"pl":"Материал стен","vl":"Блочный","p":"house_type","v":"4","pu":"hst","g":[{"gi":3,"gl":"О доме","go":3,"po":15}]},{"pl":"Год постройки","vl":"2005","p":"year_built","v":2005,"pu":"yb","g":[{"gi":1,"go":1,"po":15},{"gi":3,"gl":"О доме","go":3,"po":1}]},{"pl":"Состояние","vl":"Вторичное","p":"condition","v":"1","pu":"cnd","g":[{"gi":2,"gl":"О квартире","go":2,"po":85}]},{"pl":"Номер и дата договора","vl":"","p":"re_contract","v":"293/6 от 08.08.2024","pu":"rctr","g":[{"gi":2,"gl":"О квартире","go":2,"po":90}]}],"body":"Продается светлая, просторная 4 -комнатная квартира по улице Московская в микрорайоне Восток.\n \nПлощадь квартиры по СНБ 113,3 м2, общая площадь 104,9 м2, жилая площадь 60,4 м2, кухня 13,8 м2. Квартира расположена на 5-этаже 5-этажного блочного дома 2005 года постройки.\n \nКвартира с хорошим ремонтом. \nВходная дверь металлическая. Напольное покрытие паркет, плитка, Стены оклеены обоями. Потолки – снежка/ натяжные / подвесные. Межкомнатные двери - массив. В квартире два санузла. Один санузел совмещенный, облицован плиткой современного образца, второй санузел раздельный. Из зала выход на большую застекленную лоджию. Заменена электропроводка. Имеется сарай в подвале.\nЧистый подъезд. Двор, облагороженный детской площадкой и парковочными местами.\n \nРайон с развитой инфраструктурой. В шаговой доступности: школы, д/сады, детская поликлиника, Парк Воинов Интернационалистов, спорткомлекс «ФОК», Политехнический университет, рынок,  магазины, кафе.\nХорошее транспортное сообщение. \nЗвоните. Показ в любое удобное для Вас время.\nООО «Экспресснедвижимость-риэлт», УНП 193505113, лицензия 02240/409 от 05.03.2021 г., договор на оказание риэлтерских услуг 293/6 от 08.08.2024 г.","category":"1010","company_ad":true,"currency":"USD","images":[{"id":"0000","media_storage":"rms","path":"adim1/430209eb-7a3e-4cbd-8154-4e95dba0546f.jpg","yams_storage":false},{"id":"0000","media_storage":"rms","path":"adim1/4d947a6a-d448-4c4c-86a6-3c18858c403f.jpg","yams_storage":false},{"id":"0000","media_storage":"rms","path":"adim1/414639b4-744a-46e6-bc93-b359d75f4064.jpg","yams_storage":false},{"id":"0000","media_storage":"rms","path":"adim1/0c5fde48-00d8-4b55-8fe3-d421bf15e55f.jpg","yams_storage":false},{"id":"0000","media_storage":"rms","path":"adim1/1ac57439-9fcf-4677-bd93-4cc61e4fd1be.jpg","yams_storage":false},{"id":"0000","media_storage":"rms","path":"adim1/fc86d156-17f8-44c0-afa6-634fd140935c.jpg","yams_storage":false},{"id":"0000","media_storage":"rms","path":"adim1/cd9b99ac-1495-4d19-983a-4bda3641c3b6.jpg","yams_storage":false},{"id":"0000","media_storage":"rms","path":"adim1/07f899df-2a93-4470-ab09-f81050f579ea.jpg","yams_storage":false},{"id":"0000","media_storage":"rms","path":"adim1/5bd9dd92-94fa-4bb2-82c9-b124633f1114.jpg","yams_storage":false},{"id":"0000","media_storage":"rms","path":"adim1/381deefb-efed-4511-82fc-cdb6fc6171b8.jpg","yams_storage":false},{"id":"0000","media_storage":"rms","path":"adim1/6c5db44f-41e1-4b14-880f-bc9d5df71bb9.jpg","yams_storage":false},{"id":"0000","media_storage":"rms","path":"adim1/a0c3ee38-d47d-4585-804e-66d19d5da35f.jpg","yams_storage":false},{"id":"0000","media_storage":"rms","path":"adim1/f7a90c58-e478-4259-9406-8adae98e7a63.jpg","yams_storage":false},{"id":"0000","media_storage":"rms","path":"adim1/b97cb4d7-314e-436a-bc13-c88d8839a79c.jpg","yams_storage":false},{"id":"0000","media_storage":"rms","path":"adim1/189a2a8d-4067-4c83-b444-a6d2d551c88a.jpg","yams_storage":false},{"id":"0000","media_storage":"rms","path":"adim1/3ad18920-0673-46e7-80a2-8adfcccdb847.jpg","yams_storage":false},{"id":"0000","media_storage":"rms","path":"adim1/1ead9a61-1edb-457d-8c82-93c96ecbc499.jpg","yams_storage":false},{"id":"0000","media_storage":"rms","path":"adim1/68a158a8-ac71-4a73-a6a3-1eb3ce3e1be3.jpg","yams_storage":false},{"id":"0000","media_storage":"rms","path":"adim1/cde50c9a-6dbc-4f00-8ff6-df405d7392e7.jpg","yams_storage":false},{"id":"0000","media_storage":"rms","path":"adim1/beb77526-fbab-48a0-9e1b-4d96c70c007b.jpg","yams_storage":false},{"id":"0000","media_storage":"rms","path":"adim1/b46385a7-dd55-4c7c-a9da-f7b02a8de3ca.jpg","yams_storage":false},{"id":"0000","media_storage":"rms","path":"adim1/e0e96060-01a1-4947-9c8f-89a035d442fc.jpg","yams_storage":false},{"id":"0000","media_storage":"rms","path":"adim1/5a299961-8cd7-4a60-9141-79eeb2aa5920.jpg","yams_storage":false}],"is_mine":false,"list_id":201878576,"list_time":"2025-08-04T10:31:40Z","message_id":"adid245188207","paid_services":{"halva":false,"highlight":false,"polepos":false,"ribbons":null},"phone_hidden":false,"price_byn":"28054480","price_eur":"7771324","price_usd":"9200000","remuneration_type":"1","show_parameters":{"show_call":true,"show_chat":true,"show_import_link":true,"show_web_shop_link":true},"subject":"Продажа 4 комн. квартиры г. Брест ул. Московская","type":"sell"}}
