{"result":{"account_id":"OisUC2_GDEZxFtWsj7FEghk","account_parameters":[{"pl":"Контактное лицо","vl":"","p":"contact_person","v":"Наталья Пильник","pu":"cp"},{"pl":"Юридический адрес/Адрес регистрации","vl":"","p":"company_address","v":"Брест, ул. Советская д. 95","pu":"ca"},{"pl":"УНП","vl":"","p":"vat_number","v":"290426827","pu":"vn"},{"pl":"Имя","vl":"","p":"name","v":"ЗАО ''Альфа-Актив''","pu":"nme"},{"pl":"Адрес","vl":"","p":"address","v":"Ленинский район, Брест, Брестская область","pu":"ad","g":[{"gi":4,"gl":"Местоположение","go":4,"po":1}]}],"ad_id":235934566,"ad_link":"https://re.kufar.by/vi/235934566","ad_parameters":[{"pl":"Тип оплаты","vl":"Цена","p":"remuneration_type","v":"1","pu":"rtr"},{"pl":"Тип сделки","vl":"Продажа","p":"type","v":"sell","pu":"typ"},{"pl":"Координаты","vl":["",""],"p":"coordinates","v":[23.644796,52.130177],"pu":"gbx"},{"pl":"Категория","vl":"Квартиры","p":"category","v":1010,"pu":"cat"},{"pl":"Область","vl":"Брестская","p":"region","v":1,"pu":"rgn"},{"pl":"Город / Район","vl":"Брест","p":"area","v":"1","pu":"ar"},{"pl":"Количество комнат","vl":"4","p":"rooms","v":"4","pu":"rms","g":[{"gi":2,"gl":"О квартире","go":2,"po":1},{"gi":1,"go":1,"po":1}]},{"pl":"Цена за м²","vl":"","p":"square_meter","v":808,"pu":"psm"},{"pl":"Общая площадь","vl":"","p":"size","v":76.6,"pu":"st","g":[{"gi":2,"gl":"О квартире","go":2,"po":10},{"gi":1,"go":1,"po":20}]},{"pl":"Жилая площадь","vl":"","p":"size_living_space","v":53.7,"pu":"sls","g":[{"gi":2,"gl":"О квартире","go":2,"po":15},{"gi":1,"go":1,"po":25}]},{"pl":"Площадь кухни","vl":"7","p":"size_kitchen","v":7,"pu":"skt","g":[{"gi":2,"gl":"О квартире","go":2,"po":20},{"gi":1,"go":1,"po":30}]},{"pl":"Санузел","vl":"Раздельный","p":"bathroom","v":"1","pu":"bth","g":[{"gi":2,"gl":"О квартире","go":2,"po":25}]},{"pl":"Балкон","vl":"Лоджия","p":"balcony","v":"3","pu":"blc","g":[{"gi":2,"gl":"О квартире","go":2,"po":50}]},{"pl":"Ремонт","vl":"Косметический","p":"flat_repair","v":"1","pu":"flrp","g":[{"gi":2,"gl":"О квартире","go":2,"po":60}]},{"pl":"Этаж","vl":["4"],"p":"floor","v":[4],"pu":"fl","g":[{"gi":2,"gl":"О квартире","go":2,"po":65},{"gi":1,"go":1,"po":5}]},{"pl":"Этажность дома","vl":"5","p":"re_number_floors","v":"5","pu":"nmfl","g":[{"gi":1,"go":1,"po":10},{"gi":3,"gl":"О доме","go":3,"po":10}]},{"pl":"Материал стен","vl":"Кирпичный","p":"house_type","v":"3","pu":"hst","g":[{"gi":3,"gl":"О доме","go":3,"po":15}]},{"pl":"Год постройки","vl":"1991","p":"year_built","v":1991,"pu":"yb","g":[{"gi":1,"go":1,"po":15},{"gi":3,"gl":"О доме","go":3,"po":1}]},{"pl":"Состояние","vl":"Вторичное","p":"condition","v":"1","pu":"cnd","g":[{"gi":2,"gl":"О квартире","go":2,"po":85}]},{"pl":"Номер и дата договора","vl":"","p":"re_contract","v":"210980 от 06.02.2024","pu":"rctr","g":[{"gi":2,"gl":"О квартире","go":2,"po":90}]}],"body":" 210980\nПриобретая данный объект, ПОКУПАТЕЛЬ не платит комиссию агентству. 4- комнатная квартира, г. Брест, Сосновая ул., 1991 г.п., 4/5 кирпичный, 82,4/76,6/53,7/7 кв.м., с/у раздельный. Квартира с ремонтом в классическом стиле. Установлены стеклопакеты, новая плитка и сантехника в санузлах и на кухне, ламинат на полу в комнатах, теплый пол на кухне и коридоре, потолки- снежка+ натяжной. Вквпартире остается кухонный гарнитур. Чистый и аккуратный подъезд, благоустроенный двор с облагороженной придомовой территорией, с обустроенной детской площадкой. Район с развитой инфраструктурой, рядом с домом расположены: продовольственный магазин, аптека, школа, садик. Хорошая транспортная развязка, в шаговой доступности остановка общественного транспорта. Прекрасное предложение для большой семьи! Лот 210980 Договор  980/1 от 24.11.2021, ЗАО «Альфа-Актив», УНП , лицензия  02240/92 от 29.12.2005 на право осуществления деятельности по оказанию юридических услуг (риэлтерские услуги)","category":"1010","company_ad":true,"currency":"USD","images":[{"id":"0000","media_storage":"rms","path":"adim1/cdc5d178-f37a-4c0b-b550-85135a638b48.jpg","yams_storage":false},{"id":"0000","media_storage":"rms","path":"adim1/5d4b04bb-65e2-4004-9a6d-beeb9096f21e.jpg","yams_storage":false},{"id":"0000","media_storage":"rms","path":"adim1/be07f7d2-9fe9-43bb-98e5-0b1231304020.jpg","yams_storage":false},{"id":"0000","media_storage":"rms","path":"adim1/d21a5dec-f81a-44b4-b591-231b246f994e.jpg","yams_storage":false},{"id":"0000","media_storage":"rms","path":"adim1/a3a31546-5950-43b8-9436-f20c668a7f4c.jpg","yams_storage":false},{"id":"0000","media_storage":"rms","path":"adim1/e2f4d232-24e3-40ad-a692-a1e0daaf2c5f.jpg","yams_storage":false},{"id":"0000","media_storage":"rms","path":"adim1/f7ce4930-973e-4ee4-928a-76099781213d.jpg","yams_storage":false},{"id":"0000","media_storage":"rms","path":"adim1/baf88aac-f5c3-41e2-8564-fcf4fca8f01a.jpg","yams_storage":false},{"id":"0000","media_storage":"rms","path":"adim1/1ce9aad7-215d-4d8c-abf3-39490d3281a4.jpg","yams_storage":false},{"id":"0000","media_storage":"rms","path":"adim1/eae0c997-74e4-405c-a3d7-ddb253597d45.jpg","yams_storage":false},{"id":"0000","media_storage":"rms","path":"adim1/c9363208-90b4-4ab1-9590-21bc1fab1739.jpg","yams_storage":false},{"id":"0000","media_storage":"rms","path":"adim1/f78034cb-0993-4146-a3d7-4b3a4fe07acd.jpg","yams_storage":false},{"id":"0000","media_storage":"rms","path":"adim1/2e275097-00d5-44a8-93e9-6dd39ba262f2.jpg","yams_storage":false},{"id":"0000","media_storage":"rms","path":"adim1/76980fcb-d29b-417c-9589-42c07b68313c.jpg","yams_storage":false},{"id":"0000","media_storage":"rms","path":"adim1/4f2027d7-e87f-47bd-82dd-56d8dcdb1e3f.jpg","yams_storage":false},{"id":"0000","media_storage":"rms","path":"adim1/2cbe5760-71e3-4b6c-a3a2-74d5c8270db1.jpg","yams_storage":false},{"id":"0000","media_storage":"rms","path":"adim1/ec12f75d-c754-436e-ada4-4314bf86305a.jpg","yams_storage":false},{"id":"0000","media_storage":"rms","path":"adim1/3e00ff68-f5ad-4042-bab9-feb19ddc7e44.jpg","yams_storage":false},{"id":"0000","media_storage":"rms","path":"adim1/e94cb0d9-c717-41be-9560-ad44b6fdb3cd.jpg","yams_storage":false},{"id":"0000","media_storage":"rms","path":"adim1/d3ce7e99-20a6-4cea-b9a6-9c05bf17c3c8.jpg","yams_storage":false}],"is_mine":false,"list_id":196038087,"list_time":"2025-07-27T12:45:25Z","message_id":"adid235934566","paid_services":{"halva":false,"highlight":false,"polepos":false,"ribbons":null},"phone_hidden":false,"price_byn":"18875786","price_eur":"5228750","price_usd":"6190000","remuneration_type":"1","show_parameters":{"show_call":true,"show_chat":true,"show_import_link":true,"show_web_shop_link":true},"subject":"Брест, Сосновая ул., 4-комн.","type":"sell"}}
